pyxidoc/__init__.py
pyxidoc/pyxidoc.py
pyxidoc-0.1.dev2.dist-info/LICENSE
pyxidoc-0.1.dev2.dist-info/METADATA
pyxidoc-0.1.dev2.dist-info/WHEEL
pyxidoc-0.1.dev2.dist-info/top_level.txt
pyxidoc-0.1.dev2.dist-info/RECORD
