Metadata-Version: 2.1
Name: pyxidoc
Version: 0.1.dev2
Summary: Very simple API documentation generator written in Python3.
Home-page: http://github.com/merigor/pyxidoc
Author: merigor
Author-email: 
License: MIT
Platform: UNKNOWN
Classifier: Programming Language :: Python :: 3
Classifier: License :: OSI Approved :: MIT License
Classifier: Operating System :: OS Independent
